fastapi_middlewares/__init__.py
fastapi_middlewares/examples.py
fastapi_middlewares/itutor_google_sso/__init__.py
fastapi_middlewares/itutor_google_sso/itutor_google_sso.py
fastapi_middlewares/itutor_google_sso/templates/login.html
fastapi_middlewares/statics/dist/css/index.css
fastapi_middlewares/statics/dist/js/index.js
fastapi_middlewares/statics/dist/js/index.js.LICENSE.txt
fastapi_middlewares/statics/src/images/itutor-signature-logo.png
itutor_fastapi_middlewares-0.0.9.dist-info/METADATA
itutor_fastapi_middlewares-0.0.9.dist-info/WHEEL
itutor_fastapi_middlewares-0.0.9.dist-info/top_level.txt
itutor_fastapi_middlewares-0.0.9.dist-info/RECORD
