Metadata-Version: 2.4
Name: itutor_fastapi_middlewares
Version: 0.0.9
Summary: Package for google sso login in FastAPI
Home-page: https://github.com/bcpitutor/fastapi_middlewares
Author: Nicolas Acosta
Author-email: nicolas.acosta@itutor.com
Keywords: google-sso,fastapi
Classifier: Development Status :: 3 - Alpha
Classifier: Programming Language :: Python :: 3
Classifier: Operating System :: MacOS :: MacOS X
Classifier: Operating System :: Microsoft :: Windows
Classifier: Operating System :: POSIX :: Linux
Requires-Dist: Authlib>=1.3.1
Requires-Dist: httpx>=0.23.0
Requires-Dist: itsdangerous>=2.1.2
Requires-Dist: jinja2>=3.1.6
Requires-Dist: fastapi>=0.75.2
Dynamic: author
Dynamic: author-email
Dynamic: classifier
Dynamic: description
Dynamic: home-page
Dynamic: keywords
Dynamic: requires-dist
Dynamic: summary
